rdm/__init__.py
rdm/collect.py
rdm/first_pass_output.py
rdm/gaps.py
rdm/hooks.py
rdm/init.py
rdm/main.py
rdm/pull.py
rdm/render.py
rdm/translate.py
rdm/util.py
rdm/version.py
rdm/checklists/14971_2007.txt
rdm/checklists/14971_2019.txt
rdm/checklists/62304_2006_class_a.txt
rdm/checklists/62304_2006_class_b.txt
rdm/checklists/62304_2006_class_c.txt
rdm/checklists/62304_2015_class_a.txt
rdm/checklists/62304_2015_class_b.txt
rdm/checklists/62304_2015_class_c.txt
rdm/checklists/62304_base_class_a.txt
rdm/checklists/62304_base_class_b.txt
rdm/checklists/62304_base_class_c.txt
rdm/checklists/FDA-CYBER_2018.txt
rdm/checklists/FDA-HFE_2011.txt
rdm/checklists/FDA-SW_2005.txt
rdm/checklists/FDA-SW_2021_basic.txt
rdm/checklists/FDA-SW_2021_enhanced.txt
rdm/hook_files/commit-msg
rdm/hook_files/prepare-commit-msg
rdm/init_files/.gitignore
rdm/init_files/Dockerfile
rdm/init_files/Makefile
rdm/init_files/config.yml
rdm/init_files/docker-compose.yml
rdm/init_files/pandoc_docx.yml
rdm/init_files/pandoc_pdf.yml
rdm/init_files/template.tex
rdm/init_files/data/definitions.yml
rdm/init_files/data/device.yml
rdm/init_files/data/history.yml
rdm/init_files/data/integration_test_record.yml
rdm/init_files/data/manual_tests.yml
rdm/init_files/data/people.yml
rdm/init_files/data/predicate.yml
rdm/init_files/data/requirements.yml
rdm/init_files/data/risk.yml
rdm/init_files/data/soup.yml
rdm/init_files/data/unit_test_record.yml
rdm/init_files/data/versions.yml
rdm/init_files/data/workflow.yml
rdm/init_files/documents/cyber_security.md
rdm/init_files/documents/documentation_level_evaluation.md
rdm/init_files/documents/note_about_missing_requirements.md
rdm/init_files/documents/revision_level_history.md
rdm/init_files/documents/risk_assessment.md
rdm/init_files/documents/risk_management_plan.md
rdm/init_files/documents/risk_management_report.md
rdm/init_files/documents/software_description.md
rdm/init_files/documents/software_design_specification.md
rdm-0.11.1.dist-info/LICENSE.txt
rdm-0.11.1.dist-info/METADATA
rdm-0.11.1.dist-info/WHEEL
rdm-0.11.1.dist-info/entry_points.txt
rdm-0.11.1.dist-info/top_level.txt
rdm-0.11.1.dist-info/RECORD
